Workbook

Sheet 给定候选池内前10家
B2: A股汽车产业链候选公司：2025年度财务筛选
B3: 给定候选池内前10家｜13家符合，本表列前10家｜2025年营业收入降序｜金额单位：人民币亿元
B5: 候选公司数 | D5: 15 | E5: 符合三项条件 | G5: =COUNTIF(筛选计算!$K$2:$K$16,"符合") -> 13
B6: 数据截止日 | D6: 2026-10-26 | E6: 实际查询时间 | G6: 2026-10-27T22:27:17+08:00 至 2026-10-27T22:27:35+08:00
B7: 筛选条件：2025年营业收入＞100亿元；2025年归母净利润＞0；2025年经营活动现金流量净额＞0。缺少关键字段应标“无法判定”，本批次无缺失。
B9: 排名 | C9: 证券代码 | D9: 证券简称 | E9: 2024年营业收入 | F9: 2025年营业收入 | G9: 营收同比增速 | H9: 2025年归母净利润 | I9: 2025年经营现金流净额
B10: 1 | C10: =INDEX(筛选计算!$A$2:$A$16,MATCH($B10,筛选计算!$L$2:$L$16,0)) -> 002594.SZ | D10: =INDEX(筛选计算!$B$2:$B$16,MATCH($B10,筛选计算!$L$2:$L$16,0)) -> 比亚迪 | E10: =INDEX(筛选计算!$C$2:$C$16,MATCH($B10,筛选计算!$L$2:$L$16,0)) -> 7771.0246 | F10: =INDEX(筛选计算!$D$2:$D$16,MATCH($B10,筛选计算!$L$2:$L$16,0)) -> 8039.6496 | G10: =INDEX(筛选计算!$E$2:$E$16,MATCH($B10,筛选计算!$L$2:$L$16,0)) -> 0.034567518 | H10: =INDEX(筛选计算!$F$2:$F$16,MATCH($B10,筛选计算!$L$2:$L$16,0)) -> 326.19022 | I10: =INDEX(筛选计算!$G$2:$G$16,MATCH($B10,筛选计算!$L$2:$L$16,0)) -> 591.35544
B11: 2 | C11: =INDEX(筛选计算!$A$2:$A$16,MATCH($B11,筛选计算!$L$2:$L$16,0)) -> 600104.SH | D11: =INDEX(筛选计算!$B$2:$B$16,MATCH($B11,筛选计算!$L$2:$L$16,0)) -> 上汽集团 | E11: =INDEX(筛选计算!$C$2:$C$16,MATCH($B11,筛选计算!$L$2:$L$16,0)) -> 6140.7406 | F11: =INDEX(筛选计算!$D$2:$D$16,MATCH($B11,筛选计算!$L$2:$L$16,0)) -> 6461.521 | G11: =INDEX(筛选计算!$E$2:$E$16,MATCH($B11,筛选计算!$L$2:$L$16,0)) -> 0.052238064 | H11: =INDEX(筛选计算!$F$2:$F$16,MATCH($B11,筛选计算!$L$2:$L$16,0)) -> 101.058 | I11: =INDEX(筛选计算!$G$2:$G$16,MATCH($B11,筛选计算!$L$2:$L$16,0)) -> 343.06602
B12: 3 | C12: =INDEX(筛选计算!$A$2:$A$16,MATCH($B12,筛选计算!$L$2:$L$16,0)) -> 000338.SZ | D12: =INDEX(筛选计算!$B$2:$B$16,MATCH($B12,筛选计算!$L$2:$L$16,0)) -> 潍柴动力 | E12: =INDEX(筛选计算!$C$2:$C$16,MATCH($B12,筛选计算!$L$2:$L$16,0)) -> 2156.905 | F12: =INDEX(筛选计算!$D$2:$D$16,MATCH($B12,筛选计算!$L$2:$L$16,0)) -> 2318.0928 | G12: =INDEX(筛选计算!$E$2:$E$16,MATCH($B12,筛选计算!$L$2:$L$16,0)) -> 0.074731044 | H12: =INDEX(筛选计算!$F$2:$F$16,MATCH($B12,筛选计算!$L$2:$L$16,0)) -> 109.30504 | I12: =INDEX(筛选计算!$G$2:$G$16,MATCH($B12,筛选计算!$L$2:$L$16,0)) -> 286.81522
B13: 4 | C13: =INDEX(筛选计算!$A$2:$A$16,MATCH($B13,筛选计算!$L$2:$L$16,0)) -> 601633.SH | D13: =INDEX(筛选计算!$B$2:$B$16,MATCH($B13,筛选计算!$L$2:$L$16,0)) -> 长城汽车 | E13: =INDEX(筛选计算!$C$2:$C$16,MATCH($B13,筛选计算!$L$2:$L$16,0)) -> 2021.9547 | F13: =INDEX(筛选计算!$D$2:$D$16,MATCH($B13,筛选计算!$L$2:$L$16,0)) -> 2228.2424 | G13: =INDEX(筛选计算!$E$2:$E$16,MATCH($B13,筛选计算!$L$2:$L$16,0)) -> 0.10202388 | H13: =INDEX(筛选计算!$F$2:$F$16,MATCH($B13,筛选计算!$L$2:$L$16,0)) -> 98.652802 | I13: =INDEX(筛选计算!$G$2:$G$16,MATCH($B13,筛选计算!$L$2:$L$16,0)) -> 403.55401
B14: 5 | C14: =INDEX(筛选计算!$A$2:$A$16,MATCH($B14,筛选计算!$L$2:$L$16,0)) -> 600741.SH | D14: =INDEX(筛选计算!$B$2:$B$16,MATCH($B14,筛选计算!$L$2:$L$16,0)) -> 华域汽车 | E14: =INDEX(筛选计算!$C$2:$C$16,MATCH($B14,筛选计算!$L$2:$L$16,0)) -> 1688.5218 | F14: =INDEX(筛选计算!$D$2:$D$16,MATCH($B14,筛选计算!$L$2:$L$16,0)) -> 1839.989 | G14: =INDEX(筛选计算!$E$2:$E$16,MATCH($B14,筛选计算!$L$2:$L$16,0)) -> 0.089704002 | H14: =INDEX(筛选计算!$F$2:$F$16,MATCH($B14,筛选计算!$L$2:$L$16,0)) -> 72.072681 | I14: =INDEX(筛选计算!$G$2:$G$16,MATCH($B14,筛选计算!$L$2:$L$16,0)) -> 95.231028
B15: 6 | C15: =INDEX(筛选计算!$A$2:$A$16,MATCH($B15,筛选计算!$L$2:$L$16,0)) -> 601127.SH | D15: =INDEX(筛选计算!$B$2:$B$16,MATCH($B15,筛选计算!$L$2:$L$16,0)) -> 赛力斯 | E15: =INDEX(筛选计算!$C$2:$C$16,MATCH($B15,筛选计算!$L$2:$L$16,0)) -> 1451.7582 | F15: =INDEX(筛选计算!$D$2:$D$16,MATCH($B15,筛选计算!$L$2:$L$16,0)) -> 1650.5364 | G15: =INDEX(筛选计算!$E$2:$E$16,MATCH($B15,筛选计算!$L$2:$L$16,0)) -> 0.13692235 | H15: =INDEX(筛选计算!$F$2:$F$16,MATCH($B15,筛选计算!$L$2:$L$16,0)) -> 59.567874 | I15: =INDEX(筛选计算!$G$2:$G$16,MATCH($B15,筛选计算!$L$2:$L$16,0)) -> 289.13743
B16: 7 | C16: =INDEX(筛选计算!$A$2:$A$16,MATCH($B16,筛选计算!$L$2:$L$16,0)) -> 000625.SZ | D16: =INDEX(筛选计算!$B$2:$B$16,MATCH($B16,筛选计算!$L$2:$L$16,0)) -> 长安汽车 | E16: =INDEX(筛选计算!$C$2:$C$16,MATCH($B16,筛选计算!$L$2:$L$16,0)) -> 1597.3303 | F16: =INDEX(筛选计算!$D$2:$D$16,MATCH($B16,筛选计算!$L$2:$L$16,0)) -> 1639.998 | G16: =INDEX(筛选计算!$E$2:$E$16,MATCH($B16,筛选计算!$L$2:$L$16,0)) -> 0.02671188 | H16: =INDEX(筛选计算!$F$2:$F$16,MATCH($B16,筛选计算!$L$2:$L$16,0)) -> 40.752232 | I16: =INDEX(筛选计算!$G$2:$G$16,MATCH($B16,筛选计算!$L$2:$L$16,0)) -> 18.356734
B17: 8 | C17: =INDEX(筛选计算!$A$2:$A$16,MATCH($B17,筛选计算!$L$2:$L$16,0)) -> 600166.SH | D17: =INDEX(筛选计算!$B$2:$B$16,MATCH($B17,筛选计算!$L$2:$L$16,0)) -> 福田汽车 | E17: =INDEX(筛选计算!$C$2:$C$16,MATCH($B17,筛选计算!$L$2:$L$16,0)) -> 476.9754 | F17: =INDEX(筛选计算!$D$2:$D$16,MATCH($B17,筛选计算!$L$2:$L$16,0)) -> 612.47393 | G17: =INDEX(筛选计算!$E$2:$E$16,MATCH($B17,筛选计算!$L$2:$L$16,0)) -> 0.28407866 | H17: =INDEX(筛选计算!$F$2:$F$16,MATCH($B17,筛选计算!$L$2:$L$16,0)) -> 13.638268 | I17: =INDEX(筛选计算!$G$2:$G$16,MATCH($B17,筛选计算!$L$2:$L$16,0)) -> 18.945982
B18: 9 | C18: =INDEX(筛选计算!$A$2:$A$16,MATCH($B18,筛选计算!$L$2:$L$16,0)) -> 600699.SH | D18: =INDEX(筛选计算!$B$2:$B$16,MATCH($B18,筛选计算!$L$2:$L$16,0)) -> 均胜电子 | E18: =INDEX(筛选计算!$C$2:$C$16,MATCH($B18,筛选计算!$L$2:$L$16,0)) -> 558.63577 | F18: =INDEX(筛选计算!$D$2:$D$16,MATCH($B18,筛选计算!$L$2:$L$16,0)) -> 611.82689 | G18: =INDEX(筛选计算!$E$2:$E$16,MATCH($B18,筛选计算!$L$2:$L$16,0)) -> 0.095216088 | H18: =INDEX(筛选计算!$F$2:$F$16,MATCH($B18,筛选计算!$L$2:$L$16,0)) -> 13.358199 | I18: =INDEX(筛选计算!$G$2:$G$16,MATCH($B18,筛选计算!$L$2:$L$16,0)) -> 53.980302
B19: 10 | C19: =INDEX(筛选计算!$A$2:$A$16,MATCH($B19,筛选计算!$L$2:$L$16,0)) -> 600066.SH | D19: =INDEX(筛选计算!$B$2:$B$16,MATCH($B19,筛选计算!$L$2:$L$16,0)) -> 宇通客车 | E19: =INDEX(筛选计算!$C$2:$C$16,MATCH($B19,筛选计算!$L$2:$L$16,0)) -> 372.17587 | F19: =INDEX(筛选计算!$D$2:$D$16,MATCH($B19,筛选计算!$L$2:$L$16,0)) -> 414.26174 | G19: =INDEX(筛选计算!$E$2:$E$16,MATCH($B19,筛选计算!$L$2:$L$16,0)) -> 0.11308061 | H19: =INDEX(筛选计算!$F$2:$F$16,MATCH($B19,筛选计算!$L$2:$L$16,0)) -> 55.54482 | I19: =INDEX(筛选计算!$G$2:$G$16,MATCH($B19,筛选计算!$L$2:$L$16,0)) -> 31.966798
B21: 注：13家符合三项条件，本表仅列营收前10家；江铃汽车、德赛西威、拓普集团分列第11—13名，未补入候选池外公司。

Sheet 筛选计算
A1: 证券代码 | B1: 证券简称 | C1: 2024年营业收入（亿元） | D1: 2025年营业收入（亿元） | E1: 2025年营收同比增速 | F1: 2025年归母净利润（亿元） | G1: 2025年经营现金流净额（亿元） | H1: 营收＞100亿元 | I1: 归母净利润＞0 | J1: 经营现金流＞0 | K1: 综合筛选结果 | L1: 符合公司营收排名 | M1: 筛选说明 | N1: 2024年比较数据版本 | O1: Source Name | P1: Source URL
A2: =原始财务数据!A2 -> 002594.SZ | B2: =原始财务数据!B2 -> 比亚迪 | C2: =IF(ISNUMBER(原始财务数据!G2),原始财务数据!G2/100000000,"") -> 7771.0246 | D2: =IF(ISNUMBER(原始财务数据!H2),原始财务数据!H2/100000000,"") -> 8039.6496 | E2: =IF(OR(NOT(ISNUMBER(C2)),NOT(ISNUMBER(D2)),C2=0),"",(D2-C2)/ABS(C2)) -> 0.034567518 | F2: =IF(ISNUMBER(原始财务数据!N2),原始财务数据!N2/100000000,"") -> 326.19022 | G2: =IF(ISNUMBER(原始财务数据!P2),原始财务数据!P2/100000000,"") -> 591.35544 | H2: =IF(NOT(ISNUMBER(D2)),"无法判定",IF(D2>100,"通过","不通过")) -> 通过 | I2: =IF(NOT(ISNUMBER(F2)),"无法判定",IF(F2>0,"通过","不通过")) -> 通过 | J2: =IF(NOT(ISNUMBER(G2)),"无法判定",IF(G2>0,"通过","不通过")) -> 通过 | K2: =IF(OR(H2="无法判定",I2="无法判定",J2="无法判定"),"无法判定",IF(AND(H2="通过",I2="通过",J2="通过"),"符合","不符合")) -> 符合 | L2: =IF(K2="符合",COUNTIFS($K$2:$K$16,"符合",$D$2:$D$16,">"&D2)+COUNTIFS($K$2:K2,"符合",$D$2:D2,D2),"—") -> 1 | M2: =IF(K2="符合","入选：三项条件均通过",IF(K2="无法判定","无法判定：关键字段缺失","不符合："&IF(H2="不通过","营收≤100亿元；","")&IF(I2="不通过","归母净利润≤0；","")&IF(J2="不通过","经营现金流≤0；",""))) -> 入选：三项条件均通过 | N2: 2024年报本期数（数据库当前返回）；未提供2025年报比较期追溯调整标识 | O2: iFinD 同花顺 | P2: https://www.51ifind.com/
A3: =原始财务数据!A3 -> 600104.SH | B3: =原始财务数据!B3 -> 上汽集团 | C3: =IF(ISNUMBER(原始财务数据!G3),原始财务数据!G3/100000000,"") -> 6140.7406 | D3: =IF(ISNUMBER(原始财务数据!H3),原始财务数据!H3/100000000,"") -> 6461.521 | E3: =IF(OR(NOT(ISNUMBER(C3)),NOT(ISNUMBER(D3)),C3=0),"",(D3-C3)/ABS(C3)) -> 0.052238064 | F3: =IF(ISNUMBER(原始财务数据!N3),原始财务数据!N3/100000000,"") -> 101.058 | G3: =IF(ISNUMBER(原始财务数据!P3),原始财务数据!P3/100000000,"") -> 343.06602 | H3: =IF(NOT(ISNUMBER(D3)),"无法判定",IF(D3>100,"通过","不通过")) -> 通过 | I3: =IF(NOT(ISNUMBER(F3)),"无法判定",IF(F3>0,"通过","不通过")) -> 通过 | J3: =IF(NOT(ISNUMBER(G3)),"无法判定",IF(G3>0,"通过","不通过")) -> 通过 | K3: =IF(OR(H3="无法判定",I3="无法判定",J3="无法判定"),"无法判定",IF(AND(H3="通过",I3="通过",J3="通过"),"符合","不符合")) -> 符合 | L3: =IF(K3="符合",COUNTIFS($K$2:$K$16,"符合",$D$2:$D$16,">"&D3)+COUNTIFS($K$2:K3,"符合",$D$2:D3,D3),"—") -> 2 | M3: =IF(K3="符合","入选：三项条件均通过",IF(K3="无法判定","无法判定：关键字段缺失","不符合："&IF(H3="不通过","营收≤100亿元；","")&IF(I3="不通过","归母净利润≤0；","")&IF(J3="不通过","经营现金流≤0；",""))) -> 入选：三项条件均通过 | N3: 2024年报本期数（数据库当前返回）；未提供2025年报比较期追溯调整标识 | O3: iFinD 同花顺 | P3: https://www.51ifind.com/
A4: =原始财务数据!A4 -> 000625.SZ | B4: =原始财务数据!B4 -> 长安汽车 | C4: =IF(ISNUMBER(原始财务数据!G4),原始财务数据!G4/100000000,"") -> 1597.3303 | D4: =IF(ISNUMBER(原始财务数据!H4),原始财务数据!H4/100000000,"") -> 1639.998 | E4: =IF(OR(NOT(ISNUMBER(C4)),NOT(ISNUMBER(D4)),C4=0),"",(D4-C4)/ABS(C4)) -> 0.02671188 | F4: =IF(ISNUMBER(原始财务数据!N4),原始财务数据!N4/100000000,"") -> 40.752232 | G4: =IF(ISNUMBER(原始财务数据!P4),原始财务数据!P4/100000000,"") -> 18.356734 | H4: =IF(NOT(ISNUMBER(D4)),"无法判定",IF(D4>100,"通过","不通过")) -> 通过 | I4: =IF(NOT(ISNUMBER(F4)),"无法判定",IF(F4>0,"通过","不通过")) -> 通过 | J4: =IF(NOT(ISNUMBER(G4)),"无法判定",IF(G4>0,"通过","不通过")) -> 通过 | K4: =IF(OR(H4="无法判定",I4="无法判定",J4="无法判定"),"无法判定",IF(AND(H4="通过",I4="通过",J4="通过"),"符合","不符合")) -> 符合 | L4: =IF(K4="符合",COUNTIFS($K$2:$K$16,"符合",$D$2:$D$16,">"&D4)+COUNTIFS($K$2:K4,"符合",$D$2:D4,D4),"—") -> 7 | M4: =IF(K4="符合","入选：三项条件均通过",IF(K4="无法判定","无法判定：关键字段缺失","不符合："&IF(H4="不通过","营收≤100亿元；","")&IF(I4="不通过","归母净利润≤0；","")&IF(J4="不通过","经营现金流≤0；",""))) -> 入选：三项条件均通过 | N4: 2024年报本期数（数据库当前返回）；未提供2025年报比较期追溯调整标识 | O4: iFinD 同花顺 | P4: https://www.51ifind.com/
A5: =原始财务数据!A5 -> 601633.SH | B5: =原始财务数据!B5 -> 长城汽车 | C5: =IF(ISNUMBER(原始财务数据!G5),原始财务数据!G5/100000000,"") -> 2021.9547 | D5: =IF(ISNUMBER(原始财务数据!H5),原始财务数据!H5/100000000,"") -> 2228.2424 | E5: =IF(OR(NOT(ISNUMBER(C5)),NOT(ISNUMBER(D5)),C5=0),"",(D5-C5)/ABS(C5)) -> 0.10202388 | F5: =IF(ISNUMBER(原始财务数据!N5),原始财务数据!N5/100000000,"") -> 98.652802 | G5: =IF(ISNUMBER(原始财务数据!P5),原始财务数据!P5/100000000,"") -> 403.55401 | H5: =IF(NOT(ISNUMBER(D5)),"无法判定",IF(D5>100,"通过","不通过")) -> 通过 | I5: =IF(NOT(ISNUMBER(F5)),"无法判定",IF(F5>0,"通过","不通过")) -> 通过 | J5: =IF(NOT(ISNUMBER(G5)),"无法判定",IF(G5>0,"通过","不通过")) -> 通过 | K5: =IF(OR(H5="无法判定",I5="无法判定",J5="无法判定"),"无法判定",IF(AND(H5="通过",I5="通过",J5="通过"),"符合","不符合")) -> 符合 | L5: =IF(K5="符合",COUNTIFS($K$2:$K$16,"符合",$D$2:$D$16,">"&D5)+COUNTIFS($K$2:K5,"符合",$D$2:D5,D5),"—") -> 4 | M5: =IF(K5="符合","入选：三项条件均通过",IF(K5="无法判定","无法判定：关键字段缺失","不符合："&IF(H5="不通过","营收≤100亿元；","")&IF(I5="不通过","归母净利润≤0；","")&IF(J5="不通过","经营现金流≤0；",""))) -> 入选：三项条件均通过 | N5: 2024年报本期数（数据库当前返回）；未提供2025年报比较期追溯调整标识 | O5: iFinD 同花顺 | P5: https://www.51ifind.com/
A6: =原始财务数据!A6 -> 601238.SH | B6: =原始财务数据!B6 -> 广汽集团 | C6: =IF(ISNUMBER(原始财务数据!G6),原始财务数据!G6/100000000,"") -> 1067.9786 | D6: =IF(ISNUMBER(原始财务数据!H6),原始财务数据!H6/100000000,"") -> 956.61526 | E6: =IF(OR(NOT(ISNUMBER(C6)),NOT(ISNUMBER(D6)),C6=0),"",(D6-C6)/ABS(C6)) -> -0.10427488 | F6: =IF(ISNUMBER(原始财务数据!N6),原始财务数据!N6/100000000,"") -> -87.836212 | G6: =IF(ISNUMBER(原始财务数据!P6),原始财务数据!P6/100000000,"") -> -150.26295 | H6: =IF(NOT(ISNUMBER(D6)),"无法判定",IF(D6>100,"通过","不通过")) -> 通过 | I6: =IF(NOT(ISNUMBER(F6)),"无法判定",IF(F6>0,"通过","不通过")) -> 不通过 | J6: =IF(NOT(ISNUMBER(G6)),"无法判定",IF(G6>0,"通过","不通过")) -> 不通过 | K6: =IF(OR(H6="无法判定",I6="无法判定",J6="无法判定"),"无法判定",IF(AND(H6="通过",I6="通过",J6="通过"),"符合","不符合")) -> 不符合 | L6: =IF(K6="符合",COUNTIFS($K$2:$K$16,"符合",$D$2:$D$16,">"&D6)+COUNTIFS($K$2:K6,"符合",$D$2:D6,D6),"—") -> — | M6: =IF(K6="符合","入选：三项条件均通过",IF(K6="无法判定","无法判定：关键字段缺失","不符合："&IF(H6="不通过","营收≤100亿元；","")&IF(I6="不通过","归母净利润≤0；","")&IF(J6="不通过","经营现金流≤0；",""))) -> 不符合：归母净利润≤0；经营现金流≤0； | N6: 2024年报本期数（数据库当前返回）；未提供2025年报比较期追溯调整标识 | O6: iFinD 同花顺 | P6: https://www.51ifind.com/
A7: =原始财务数据!A7 -> 601127.SH | B7: =原始财务数据!B7 -> 赛力斯 | C7: =IF(ISNUMBER(原始财务数据!G7),原始财务数据!G7/100000000,"") -> 1451.7582 | D7: =IF(ISNUMBER(原始财务数据!H7),原始财务数据!H7/100000000,"") -> 1650.5364 | E7: =IF(OR(NOT(ISNUMBER(C7)),NOT(ISNUMBER(D7)),C7=0),"",(D7-C7)/ABS(C7)) -> 0.13692235 | F7: =IF(ISNUMBER(原始财务数据!N7),原始财务数据!N7/100000000,"") -> 59.567874 | G7: =IF(ISNUMBER(原始财务数据!P7),原始财务数据!P7/100000000,"") -> 289.13743 | H7: =IF(NOT(ISNUMBER(D7)),"无法判定",IF(D7>100,"通过","不通过")) -> 通过 | I7: =IF(NOT(ISNUMBER(F7)),"无法判定",IF(F7>0,"通过","不通过")) -> 通过 | J7: =IF(NOT(ISNUMBER(G7)),"无法判定",IF(G7>0,"通过","不通过")) -> 通过 | K7: =IF(OR(H7="无法判定",I7="无法判定",J7="无法判定"),"无法判定",IF(AND(H7="通过",I7="通过",J7="通过"),"符合","不符合")) -> 符合 | L7: =IF(K7="符合",COUNTIFS($K$2:$K$16,"符合",$D$2:$D$16,">"&D7)+COUNTIFS($K$2:K7,"符合",$D$2:D7,D7),"—") -> 6 | M7: =IF(K7="符合","入选：三项条件均通过",IF(K7="无法判定","无法判定：关键字段缺失","不符合："&IF(H7="不通过","营收≤100亿元；","")&IF(I7="不通过","归母净利润≤0；","")&IF(J7="不通过","经营现金流≤0；",""))) -> 入选：三项条件均通过 | N7: 2024年报本期数（数据库当前返回）；未提供2025年报比较期追溯调整标识 | O7: iFinD 同花顺 | P7: https://www.51ifind.com/
A8: =原始财务数据!A8 -> 600418.SH | B8: =原始财务数据!B8 -> 江淮汽车 | C8: =IF(ISNUMBER(原始财务数据!G8),原始财务数据!G8/100000000,"") -> 421.15892 | D8: =IF(ISNUMBER(原始财务数据!H8),原始财务数据!H8/100000000,"") -> 464.75721 | E8: =IF(OR(NOT(ISNUMBER(C8)),NOT(ISNUMBER(D8)),C8=0),"",(D8-C8)/ABS(C8)) -> 0.10351981 | F8: =IF(ISNUMBER(原始财务数据!N8),原始财务数据!N8/100000000,"") -> -17.025735 | G8: =IF(ISNUMBER(原始财务数据!P8),原始财务数据!P8/100000000,"") -> 33.946543 | H8: =IF(NOT(ISNUMBER(D8)),"无法判定",IF(D8>100,"通过","不通过")) -> 通过 | I8: =IF(NOT(ISNUMBER(F8)),"无法判定",IF(F8>0,"通过","不通过")) -> 不通过 | J8: =IF(NOT(ISNUMBER(G8)),"无法判定",IF(G8>0,"通过","不通过")) -> 通过 | K8: =IF(OR(H8="无法判定",I8="无法判定",J8="无法判定"),"无法判定",IF(AND(H8="通过",I8="通过",J8="通过"),"符合","不符合")) -> 不符合 | L8: =IF(K8="符合",COUNTIFS($K$2:$K$16,"符合",$D$2:$D$16,">"&D8)+COUNTIFS($K$2:K8,"符合",$D$2:D8,D8),"—") -> — | M8: =IF(K8="符合","入选：三项条件均通过",IF(K8="无法判定","无法判定：关键字段缺失","不符合："&IF(H8="不通过","营收≤100亿元；","")&IF(I8="不通过","归母净利润≤0；","")&IF(J8="不通过","经营现金流≤0；",""))) -> 不符合：归母净利润≤0； | N8: 2024年报本期数（数据库当前返回）；未提供2025年报比较期追溯调整标识 | O8: iFinD 同花顺 | P8: https://www.51ifind.com/
A9: =原始财务数据!A9 -> 000550.SZ | B9: =原始财务数据!B9 -> 江铃汽车 | C9: =IF(ISNUMBER(原始财务数据!G9),原始财务数据!G9/100000000,"") -> 383.74161 | D9: =IF(ISNUMBER(原始财务数据!H9),原始财务数据!H9/100000000,"") -> 391.6991 | E9: =IF(OR(NOT(ISNUMBER(C9)),NOT(ISNUMBER(D9)),C9=0),"",(D9-C9)/ABS(C9)) -> 0.020736589 | F9: =IF(ISNUMBER(原始财务数据!N9),原始财务数据!N9/100000000,"") -> 11.874657 | G9: =IF(ISNUMBER(原始财务数据!P9),原始财务数据!P9/100000000,"") -> 24.119113 | H9: =IF(NOT(ISNUMBER(D9)),"无法判定",IF(D9>100,"通过","不通过")) -> 通过 | I9: =IF(NOT(ISNUMBER(F9)),"无法判定",IF(F9>0,"通过","不通过")) -> 通过 | J9: =IF(NOT(ISNUMBER(G9)),"无法判定",IF(G9>0,"通过","不通过")) -> 通过 | K9: =IF(OR(H9="无法判定",I9="无法判定",J9="无法判定"),"无法判定",IF(AND(H9="通过",I9="通过",J9="通过"),"符合","不符合")) -> 符合 | L9: =IF(K9="符合",COUNTIFS($K$2:$K$16,"符合",$D$2:$D$16,">"&D9)+COUNTIFS($K$2:K9,"符合",$D$2:D9,D9),"—") -> 11 | M9: =IF(K9="符合","入选：三项条件均通过",IF(K9="无法判定","无法判定：关键字段缺失","不符合："&IF(H9="不通过","营收≤100亿元；","")&IF(I9="不通过","归母净利润≤0；","")&IF(J9="不通过","经营现金流≤0；",""))) -> 入选：三项条件均通过 | N9: 2024年报本期数（数据库当前返回）；未提供2025年报比较期追溯调整标识 | O9: iFinD 同花顺 | P9: https://www.51ifind.com/
A10: =原始财务数据!A10 -> 600066.SH | B10: =原始财务数据!B10 -> 宇通客车 | C10: =IF(ISNUMBER(原始财务数据!G10),原始财务数据!G10/100000000,"") -> 372.17587 | D10: =IF(ISNUMBER(原始财务数据!H10),原始财务数据!H10/100000000,"") -> 414.26174 | E10: =IF(OR(NOT(ISNUMBER(C10)),NOT(ISNUMBER(D10)),C10=0),"",(D10-C10)/ABS(C10)) -> 0.11308061 | F10: =IF(ISNUMBER(原始财务数据!N10),原始财务数据!N10/100000000,"") -> 55.54482 | G10: =IF(ISNUMBER(原始财务数据!P10),原始财务数据!P10/100000000,"") -> 31.966798 | H10: =IF(NOT(ISNUMBER(D10)),"无法判定",IF(D10>100,"通过","不通过")) -> 通过 | I10: =IF(NOT(ISNUMBER(F10)),"无法判定",IF(F10>0,"通过","不通过")) -> 通过 | J10: =IF(NOT(ISNUMBER(G10)),"无法判定",IF(G10>0,"通过","不通过")) -> 通过 | K10: =IF(OR(H10="无法判定",I10="无法判定",J10="无法判定"),"无法判定",IF(AND(H10="通过",I10="通过",J10="通过"),"符合","不符合")) -> 符合 | L10: =IF(K10="符合",COUNTIFS($K$2:$K$16,"符合",$D$2:$D$16,">"&D10)+COUNTIFS($K$2:K10,"符合",$D$2:D10,D10),"—") -> 10 | M10: =IF(K10="符合","入选：三项条件均通过",IF(K10="无法判定","无法判定：关键字段缺失","不符合："&IF(H10="不通过","营收≤100亿元；","")&IF(I10="不通过","归母净利润≤0；","")&IF(J10="不通过","经营现金流≤0；",""))) -> 入选：三项条件均通过 | N10: 2024年报本期数（数据库当前返回）；未提供2025年报比较期追溯调整标识 | O10: iFinD 同花顺 | P10: https://www.51ifind.com/
A11: =原始财务数据!A11 -> 600166.SH | B11: =原始财务数据!B11 -> 福田汽车 | C11: =IF(ISNUMBER(原始财务数据!G11),原始财务数据!G11/100000000,"") -> 476.9754 | D11: =IF(ISNUMBER(原始财务数据!H11),原始财务数据!H11/100000000,"") -> 612.47393 | E11: =IF(OR(NOT(ISNUMBER(C11)),NOT(ISNUMBER(D11)),C11=0),"",(D11-C11)/ABS(C11)) -> 0.28407866 | F11: =IF(ISNUMBER(原始财务数据!N11),原始财务数据!N11/100000000,"") -> 13.638268 | G11: =IF(ISNUMBER(原始财务数据!P11),原始财务数据!P11/100000000,"") -> 18.945982 | H11: =IF(NOT(ISNUMBER(D11)),"无法判定",IF(D11>100,"通过","不通过")) -> 通过 | I11: =IF(NOT(ISNUMBER(F11)),"无法判定",IF(F11>0,"通过","不通过")) -> 通过 | J11: =IF(NOT(ISNUMBER(G11)),"无法判定",IF(G11>0,"通过","不通过")) -> 通过 | K11: =IF(OR(H11="无法判定",I11="无法判定",J11="无法判定"),"无法判定",IF(AND(H11="通过",I11="通过",J11="通过"),"符合","不符合")) -> 符合 | L11: =IF(K11="符合",COUNTIFS($K$2:$K$16,"符合",$D$2:$D$16,">"&D11)+COUNTIFS($K$2:K11,"符合",$D$2:D11,D11),"—") -> 8 | M11: =IF(K11="符合","入选：三项条件均通过",IF(K11="无法判定","无法判定：关键字段缺失","不符合："&IF(H11="不通过","营收≤100亿元；","")&IF(I11="不通过","归母净利润≤0；","")&IF(J11="不通过","经营现金流≤0；",""))) -> 入选：三项条件均通过 | N11: 2024年报本期数（数据库当前返回）；未提供2025年报比较期追溯调整标识 | O11: iFinD 同花顺 | P11: https://www.51ifind.com/
A12: =原始财务数据!A12 -> 000338.SZ | B12: =原始财务数据!B12 -> 潍柴动力 | C12: =IF(ISNUMBER(原始财务数据!G12),原始财务数据!G12/100000000,"") -> 2156.905 | D12: =IF(ISNUMBER(原始财务数据!H12),原始财务数据!H12/100000000,"") -> 2318.0928 | E12: =IF(OR(NOT(ISNUMBER(C12)),NOT(ISNUMBER(D12)),C12=0),"",(D12-C12)/ABS(C12)) -> 0.074731044 | F12: =IF(ISNUMBER(原始财务数据!N12),原始财务数据!N12/100000000,"") -> 109.30504 | G12: =IF(ISNUMBER(原始财务数据!P12),原始财务数据!P12/100000000,"") -> 286.81522 | H12: =IF(NOT(ISNUMBER(D12)),"无法判定",IF(D12>100,"通过","不通过")) -> 通过 | I12: =IF(NOT(ISNUMBER(F12)),"无法判定",IF(F12>0,"通过","不通过")) -> 通过 | J12: =IF(NOT(ISNUMBER(G12)),"无法判定",IF(G12>0,"通过","不通过")) -> 通过 | K12: =IF(OR(H12="无法判定",I12="无法判定",J12="无法判定"),"无法判定",IF(AND(H12="通过",I12="通过",J12="通过"),"符合","不符合")) -> 符合 | L12: =IF(K12="符合",COUNTIFS($K$2:$K$16,"符合",$D$2:$D$16,">"&D12)+COUNTIFS($K$2:K12,"符合",$D$2:D12,D12),"—") -> 3 | M12: =IF(K12="符合","入选：三项条件均通过",IF(K12="无法判定","无法判定：关键字段缺失","不符合："&IF(H12="不通过","营收≤100亿元；","")&IF(I12="不通过","归母净利润≤0；","")&IF(J12="不通过","经营现金流≤0；",""))) -> 入选：三项条件均通过 | N12: 2024年报本期数（数据库当前返回）；未提供2025年报比较期追溯调整标识 | O12: iFinD 同花顺 | P12: https://www.51ifind.com/
A13: =原始财务数据!A13 -> 600741.SH | B13: =原始财务数据!B13 -> 华域汽车 | C13: =IF(ISNUMBER(原始财务数据!G13),原始财务数据!G13/100000000,"") -> 1688.5218 | D13: =IF(ISNUMBER(原始财务数据!H13),原始财务数据!H13/100000000,"") -> 1839.989 | E13: =IF(OR(NOT(ISNUMBER(C13)),NOT(ISNUMBER(D13)),C13=0),"",(D13-C13)/ABS(C13)) -> 0.089704002 | F13: =IF(ISNUMBER(原始财务数据!N13),原始财务数据!N13/100000000,"") -> 72.072681 | G13: =IF(ISNUMBER(原始财务数据!P13),原始财务数据!P13/100000000,"") -> 95.231028 | H13: =IF(NOT(ISNUMBER(D13)),"无法判定",IF(D13>100,"通过","不通过")) -> 通过 | I13: =IF(NOT(ISNUMBER(F13)),"无法判定",IF(F13>0,"通过","不通过")) -> 通过 | J13: =IF(NOT(ISNUMBER(G13)),"无法判定",IF(G13>0,"通过","不通过")) -> 通过 | K13: =IF(OR(H13="无法判定",I13="无法判定",J13="无法判定"),"无法判定",IF(AND(H13="通过",I13="通过",J13="通过"),"符合","不符合")) -> 符合 | L13: =IF(K13="符合",COUNTIFS($K$2:$K$16,"符合",$D$2:$D$16,">"&D13)+COUNTIFS($K$2:K13,"符合",$D$2:D13,D13),"—") -> 5 | M13: =IF(K13="符合","入选：三项条件均通过",IF(K13="无法判定","无法判定：关键字段缺失","不符合："&IF(H13="不通过","营收≤100亿元；","")&IF(I13="不通过","归母净利润≤0；","")&IF(J13="不通过","经营现金流≤0；",""))) -> 入选：三项条件均通过 | N13: 2024年报本期数（数据库当前返回）；未提供2025年报比较期追溯调整标识 | O13: iFinD 同花顺 | P13: https://www.51ifind.com/
... A16: =原始财务数据!A16 -> 600699.SH | B16: =原始财务数据!B16 -> 均胜电子 | C16: =IF(ISNUMBER(原始财务数据!G16),原始财务数据!G16/100000000,"") -> 558.63577 | D16: =IF(ISNUMBER(原始财务数据!H16),原始财务数据!H16/100000000,"") -> 611.82689 | E16: =IF(OR(NOT(ISNUMBER(C16)),NOT(ISNUMBER(D16)),C16=0),"",(D16-C16)/ABS(C16)) -> 0.095216088 | F16: =IF(ISNUMBER(原始财务数据!N16),原始财务数据!N16/100000000,"") -> 13.358199 | G16: =IF(ISNUMBER(原始财务数据!P16),原始财务数据!P16/100000000,"") -> 53.980302 | H16: =IF(NOT(ISNUMBER(D16)),"无法判定",IF(D16>100,"通过","不通过")) -> 通过 | I16: =IF(NOT(ISNUMBER(F16)),"无法判定",IF(F16>0,"通过","不通过")) -> 通过 | J16: =IF(NOT(ISNUMBER(G16)),"无法判定",IF(G16>0,"通过","不通过")) -> 通过 | K16: =IF(OR(H16="无法判定",I16="无法判定",J16="无法判定"),"无法判定",IF(AND(H16="通过",I16="通过",J16="通过"),"符合","不符合")) -> 符合 | L16: =IF(K16="符合",COUNTIFS($K$2:$K$16,"符合",$D$2:$D$16,">"&D16)+COUNTIFS($K$2:K16,"符合",$D$2:D16,D16),"—") -> 9 | M16: =IF(K16="符合","入选：三项条件均通过",IF(K16="无法判定","无法判定：关键字段缺失","不符合："&IF(H16="不通过","营收≤100亿元；","")&IF(I16="不通过","归母净利润≤0；","")&IF(J16="不通过","经营现金流≤0；",""))) -> 入选：三项条件均通过 | N16: 2024年报本期数（数据库当前返回）；未提供2025年报比较期追溯调整标识 | O16: iFinD 同花顺 | P16: https://www.51ifind.com/

Sheet 原始财务数据
A1: 证券代码 | B1: 证券简称（数据库） | C1: 证券简称（输入） | D1: 身份核对 | E1: 2024报告期 | F1: 2025报告期 | G1: 2024营业收入（元） | H1: 2025营业收入（元） | I1: 2024营业总收入（元） | J1: 2025营业总收入（元） | K1: 2024净利润（元） | L1: 2025净利润（元） | M1: 2024归母净利润（元） | N1: 2025归母净利润（元） | O1: 2024经营现金流净额（元） | P1: 2025经营现金流净额（元） | Q1: 2024利润表来源 | R1: 2024现金流来源 | S1: 2025利润表来源 | T1: 2025现金流来源 | U1: 证券简称来源 | V1: Source Name | W1: Source URL
A2: 002594.SZ | B2: 比亚迪 | C2: 比亚迪 | D2: 一致 | E2: 2024-12-31 | F2: 2025-12-31 | G2: 777102455000 | H2: 803964958000 | I2: 777102455000 | J2: 803964958000 | K2: 41587940000 | L2: 33760758000 | M2: 40254346000 | N2: 32619022000 | O2: 133453873000 | P2: 59135544000 | Q2: output/raw/income_statement_batch1_2024.csv | R2: output/raw/cash_flow_batch1_2024.csv | S2: output/raw/income_statement_batch1_2025.csv | T2: output/raw/cash_flow_batch1_2025.csv | U2: output/raw/stock_info_batch1.csv | V2: iFinD 同花顺 | W2: https://www.51ifind.com/
A3: 600104.SH | B3: 上汽集团 | C3: 上汽集团 | D3: 一致 | E3: 2024-12-31 | F3: 2025-12-31 | G3: 6.1407406e+11 | H3: 6.461521e+11 | I3: 6.2758995e+11 | J3: 6.5624381e+11 | K3: 5.8333213e+09 | L3: 1.7443924e+10 | M3: 1.6663768e+09 | N3: 1.01058e+10 | O3: 6.926779e+10 | P3: 3.4306602e+10 | Q3: output/raw/income_statement_batch1_2024.csv | R3: output/raw/cash_flow_batch1_2024.csv | S3: output/raw/income_statement_batch1_2025.csv | T3: output/raw/cash_flow_batch1_2025.csv | U3: output/raw/stock_info_batch1.csv | V3: iFinD 同花顺 | W3: https://www.51ifind.com/
A4: 000625.SZ | B4: 长安汽车 | C4: 长安汽车 | D4: 一致 | E4: 2024-12-31 | F4: 2025-12-31 | G4: 1.5973303e+11 | H4: 1.639998e+11 | I4: 1.5973303e+11 | J4: 1.639998e+11 | K4: 6.1041745e+09 | L4: 3.1674918e+09 | M4: 7.3213639e+09 | N4: 4.0752232e+09 | O4: 4.8493988e+09 | P4: 1.8356734e+09 | Q4: output/raw/income_statement_batch1_2024.csv | R4: output/raw/cash_flow_batch1_2024.csv | S4: output/raw/income_statement_batch1_2025.csv | T4: output/raw/cash_flow_batch1_2025.csv | U4: output/raw/stock_info_batch1.csv | V4: iFinD 同花顺 | W4: https://www.51ifind.com/
A5: 601633.SH | B5: 长城汽车 | C5: 长城汽车 | D5: 一致 | E5: 2024-12-31 | F5: 2025-12-31 | G5: 2.0219547e+11 | H5: 2.2282424e+11 | I5: 2.0219547e+11 | J5: 2.2282424e+11 | K5: 1.2692439e+10 | L5: 9.8652802e+09 | M5: 1.2692204e+10 | N5: 9.8652802e+09 | O5: 2.7782626e+10 | P5: 4.0355401e+10 | Q5: output/raw/income_statement_batch2_2024.csv | R5: output/raw/cash_flow_batch2_2024.csv | S5: output/raw/income_statement_batch2_2025.csv | T5: output/raw/cash_flow_batch2_2025.csv | U5: output/raw/stock_info_batch2.csv | V5: iFinD 同花顺 | W5: https://www.51ifind.com/
A6: 601238.SH | B6: 广汽集团 | C6: 广汽集团 | D6: 一致 | E6: 2024-12-31 | F6: 2025-12-31 | G6: 106797859228 | H6: 95661525530 | I6: 107783806936 | J6: 96542390397 | K6: -494043219 | L6: -11481727514 | M6: 823581893 | N6: -8783621243 | O6: 10918597387 | P6: -15026294544 | Q6: output/raw/income_statement_batch2_2024.csv | R6: output/raw/cash_flow_batch2_2024.csv | S6: output/raw/income_statement_batch2_2025.csv | T6: output/raw/cash_flow_batch2_2025.csv | U6: output/raw/stock_info_batch2.csv | V6: iFinD 同花顺 | W6: https://www.51ifind.com/
A7: 601127.SH | B7: 赛力斯 | C7: 赛力斯 | D7: 一致 | E7: 2024-12-31 | F7: 2025-12-31 | G7: 1.4517582e+11 | H7: 1.6505364e+11 | I7: 1.4517582e+11 | J7: 1.6505364e+11 | K7: 4.7401164e+09 | L7: 6.1467398e+09 | M7: 5.9459454e+09 | N7: 5.9567874e+09 | O7: 2.2515265e+10 | P7: 2.8913743e+10 | Q7: output/raw/income_statement_batch2_2024.csv | R7: output/raw/cash_flow_batch2_2024.csv | S7: output/raw/income_statement_batch2_2025.csv | T7: output/raw/cash_flow_batch2_2025.csv | U7: output/raw/stock_info_batch2.csv | V7: iFinD 同花顺 | W7: https://www.51ifind.com/
A8: 600418.SH | B8: 江淮汽车 | C8: 江淮汽车 | D8: 一致 | E8: 2024-12-31 | F8: 2025-12-31 | G8: 4.2115892e+10 | H8: 4.6475721e+10 | I8: 4.2202287e+10 | J8: 4.6568671e+10 | K8: -1.9935168e+09 | L8: -1.7715152e+09 | M8: -1.78416e+09 | N8: -1.7025735e+09 | O8: 2.7114726e+09 | P8: 3.3946543e+09 | Q8: output/raw/income_statement_batch3_2024.csv | R8: output/raw/cash_flow_batch3_2024.csv | S8: output/raw/income_statement_batch3_2025.csv | T8: output/raw/cash_flow_batch3_2025.csv | U8: output/raw/stock_info_batch3.csv | V8: iFinD 同花顺 | W8: https://www.51ifind.com/
A9: 000550.SZ | B9: 江铃汽车 | C9: 江铃汽车 | D9: 一致 | E9: 2024-12-31 | F9: 2025-12-31 | G9: 38374160748 | H9: 39169909929 | I9: 38374160748 | J9: 39169909929 | K9: 1205176809 | L9: 819372718 | M9: 1537139024 | N9: 1187465719 | O9: 2633384217 | P9: 2411911290 | Q9: output/raw/income_statement_batch3_2024.csv | R9: output/raw/cash_flow_batch3_2024.csv | S9: output/raw/income_statement_batch3_2025.csv | T9: output/raw/cash_flow_batch3_2025.csv | U9: output/raw/stock_info_batch3.csv | V9: iFinD 同花顺 | W9: https://www.51ifind.com/
A10: 600066.SH | B10: 宇通客车 | C10: 宇通客车 | D10: 一致 | E10: 2024-12-31 | F10: 2025-12-31 | G10: 3.7217587e+10 | H10: 4.1426174e+10 | I10: 3.7217587e+10 | J10: 4.1426174e+10 | K10: 4.1539258e+09 | L10: 5.6251763e+09 | M10: 4.1161944e+09 | N10: 5.554482e+09 | O10: 7.2105903e+09 | P10: 3.1966798e+09 | Q10: output/raw/income_statement_batch3_2024.csv | R10: output/raw/cash_flow_batch3_2024.csv | S10: output/raw/income_statement_batch3_2025.csv | T10: output/raw/cash_flow_batch3_2025.csv | U10: output/raw/stock_info_batch3.csv | V10: iFinD 同花顺 | W10: https://www.51ifind.com/
A11: 600166.SH | B11: 福田汽车 | C11: 福田汽车 | D11: 一致 | E11: 2024-12-31 | F11: 2025-12-31 | G11: 4.769754e+10 | H11: 6.1247393e+10 | I11: 4.769754e+10 | J11: 6.1247393e+10 | K11: 41913727 | L11: 1.2858191e+09 | M11: 80542789 | N11: 1.3638268e+09 | O11: 1.3053504e+09 | P11: 1.8945982e+09 | Q11: output/raw/income_statement_batch4_2024.csv | R11: output/raw/cash_flow_batch4_2024.csv | S11: output/raw/income_statement_batch4_2025.csv | T11: output/raw/cash_flow_batch4_2025.csv | U11: output/raw/stock_info_batch4.csv | V11: iFinD 同花顺 | W11: https://www.51ifind.com/
A12: 000338.SZ | B12: 潍柴动力 | C12: 潍柴动力 | D12: 一致 | E12: 2024-12-31 | F12: 2025-12-31 | G12: 2.156905e+11 | H12: 2.3180928e+11 | I12: 2.156905e+11 | J12: 2.3180928e+11 | K12: 1.4277682e+10 | L12: 1.3680319e+10 | M12: 1.1403289e+10 | N12: 1.0930504e+10 | O12: 2.6094124e+10 | P12: 2.8681522e+10 | Q12: output/raw/income_statement_batch4_2024.csv | R12: output/raw/cash_flow_batch4_2024.csv | S12: output/raw/income_statement_batch4_2025.csv | T12: output/raw/cash_flow_batch4_2025.csv | U12: output/raw/stock_info_batch4.csv | V12: iFinD 同花顺 | W12: https://www.51ifind.com/
A13: 600741.SH | B13: 华域汽车 | C13: 华域汽车 | D13: 一致 | E13: 2024-12-31 | F13: 2025-12-31 | G13: 1.6885218e+11 | H13: 1.839989e+11 | I13: 1.6885218e+11 | J13: 1.839989e+11 | K13: 7.4822643e+09 | L13: 8.2265923e+09 | M13: 6.690703e+09 | N13: 7.2072681e+09 | O13: 8.1398478e+09 | P13: 9.5231028e+09 | Q13: output/raw/income_statement_batch4_2024.csv | R13: output/raw/cash_flow_batch4_2024.csv | S13: output/raw/income_statement_batch4_2025.csv | T13: output/raw/cash_flow_batch4_2025.csv | U13: output/raw/stock_info_batch4.csv | V13: iFinD 同花顺 | W13: https://www.51ifind.com/
... A16: 600699.SH | B16: 均胜电子 | C16: 均胜电子 | D16: 一致 | E16: 2024-12-31 | F16: 2025-12-31 | G16: 5.5863577e+10 | H16: 6.1182689e+10 | I16: 5.5863577e+10 | J16: 6.1182689e+10 | K16: 1.3262815e+09 | L16: 1.6155461e+09 | M16: 9.604696e+08 | N16: 1.3358199e+09 | O16: 4.6018043e+09 | P16: 5.3980302e+09 | Q16: output/raw/income_statement_batch5_2024.csv | R16: output/raw/cash_flow_batch5_2024.csv | S16: output/raw/income_statement_batch5_2025.csv | T16: output/raw/cash_flow_batch5_2025.csv | U16: output/raw/stock_info_batch5.csv | V16: iFinD 同花顺 | W16: https://www.51ifind.com/

Sheet 查询口径与来源
B2: 查询口径、字段映射与来源
B4: 项目 | C4: 说明
B5: 数据源 | C5: iFinD（同花顺），通过 ifind_get_stock_info 与 ifind_get_financial_statements 实际接口查询；未使用网页搜索摘要或估计值。
B6: 候选范围 | C6: 仅限用户给定15家A股公司，以证券代码为准；未获取全市场或行业成分清单。
B7: 身份核对 | C7: 证券简称由 ifind_get_stock_info 按 request_time=2026-10-26 查询，15家均与输入简称一致。
B8: 报告期 | C8: 2025-12-31年度合并财务报表；2024-12-31年度合并财务报表作为营收同比比较期。
B9: 数据截止日 | C9: 2026-10-26（按用户指定口径）。
B10: 实际查询时间 | C10: 2026-10-27T22:27:17+08:00 至 2026-10-27T22:27:35+08:00（本地时区，ISO 8601）。
B11: 金额单位 | C11: 原始财务数据表保留人民币元；筛选计算与前10家表统一换算为人民币亿元，1亿元=100,000,000元。
B12: 营业收入字段 | C12: ths_revenue_stock（营业收入），筛选与同比均不使用 ths_operating_total_revenue_stock（营业总收入）。
B13: 归母净利润字段 | C13: ths_np_atoopc_stock（归属于母公司股东的净利润），不以 ths_np_stock（净利润）替代。
B14: 经营现金流字段 | C14: ths_ncf_from_oa_stock（经营活动产生的现金流量净额）。
B15: 营收增速公式 | C15: （2025年营业收入－2024年营业收入）÷ABS（2024年营业收入）。Excel公式见“筛选计算”E列。
... B24: 结果命名 | C24: 给定候选池内前10家；13家符合三项条件，按2025年营业收入列示前10家，不补入其他公司。

Sheet 查询记录
A1: 序号 | B1: 批次标签 | C1: API | D1: 本地开始时间 | E1: 本地结束时间 | F1: 返回码 | G1: 参数文件 | H1: 原始响应文件
A2: 1 | B2: stock_info_batch1 | C2: ifind_get_stock_info | D2: 2026-10-27T22:27:17+08:00 | E2: 2026-10-27T22:27:18+08:00 | F2: 0 | G2: output\raw\stock_info_batch1_params.json | H2: output\raw\stock_info_batch1_response.txt
A3: 2 | B3: financials_batch1_2025 | C3: ifind_get_financial_statements | D3: 2026-10-27T22:27:18+08:00 | E3: 2026-10-27T22:27:18+08:00 | F3: 0 | G3: output\raw\financials_batch1_2025_params.json | H3: output\raw\financials_batch1_2025_response.txt
A4: 3 | B4: financials_batch1_2024 | C4: ifind_get_financial_statements | D4: 2026-10-27T22:27:18+08:00 | E4: 2026-10-27T22:27:19+08:00 | F4: 0 | G4: output\raw\financials_batch1_2024_params.json | H4: output\raw\financials_batch1_2024_response.txt
A5: 4 | B5: stock_info_batch2 | C5: ifind_get_stock_info | D5: 2026-10-27T22:27:19+08:00 | E5: 2026-10-27T22:27:19+08:00 | F5: 0 | G5: output\raw\stock_info_batch2_params.json | H5: output\raw\stock_info_batch2_response.txt
A6: 5 | B6: financials_batch2_2025 | C6: ifind_get_financial_statements | D6: 2026-10-27T22:27:19+08:00 | E6: 2026-10-27T22:27:21+08:00 | F6: 0 | G6: output\raw\financials_batch2_2025_params.json | H6: output\raw\financials_batch2_2025_response.txt
A7: 6 | B7: financials_batch2_2024 | C7: ifind_get_financial_statements | D7: 2026-10-27T22:27:21+08:00 | E7: 2026-10-27T22:27:23+08:00 | F7: 0 | G7: output\raw\financials_batch2_2024_params.json | H7: output\raw\financials_batch2_2024_response.txt
A8: 7 | B8: stock_info_batch3 | C8: ifind_get_stock_info | D8: 2026-10-27T22:27:23+08:00 | E8: 2026-10-27T22:27:24+08:00 | F8: 0 | G8: output\raw\stock_info_batch3_params.json | H8: output\raw\stock_info_batch3_response.txt
A9: 8 | B9: financials_batch3_2025 | C9: ifind_get_financial_statements | D9: 2026-10-27T22:27:24+08:00 | E9: 2026-10-27T22:27:26+08:00 | F9: 0 | G9: output\raw\financials_batch3_2025_params.json | H9: output\raw\financials_batch3_2025_response.txt
A10: 9 | B10: financials_batch3_2024 | C10: ifind_get_financial_statements | D10: 2026-10-27T22:27:26+08:00 | E10: 2026-10-27T22:27:27+08:00 | F10: 0 | G10: output\raw\financials_batch3_2024_params.json | H10: output\raw\financials_batch3_2024_response.txt
A11: 10 | B11: stock_info_batch4 | C11: ifind_get_stock_info | D11: 2026-10-27T22:27:27+08:00 | E11: 2026-10-27T22:27:28+08:00 | F11: 0 | G11: output\raw\stock_info_batch4_params.json | H11: output\raw\stock_info_batch4_response.txt
A12: 11 | B12: financials_batch4_2025 | C12: ifind_get_financial_statements | D12: 2026-10-27T22:27:28+08:00 | E12: 2026-10-27T22:27:30+08:00 | F12: 0 | G12: output\raw\financials_batch4_2025_params.json | H12: output\raw\financials_batch4_2025_response.txt
A13: 12 | B13: financials_batch4_2024 | C13: ifind_get_financial_statements | D13: 2026-10-27T22:27:30+08:00 | E13: 2026-10-27T22:27:31+08:00 | F13: 0 | G13: output\raw\financials_batch4_2024_params.json | H13: output\raw\financials_batch4_2024_response.txt
... A16: 15 | B16: financials_batch5_2024 | C16: ifind_get_financial_statements | D16: 2026-10-27T22:27:33+08:00 | E16: 2026-10-27T22:27:35+08:00 | F16: 0 | G16: output\raw\financials_batch5_2024_params.json | H16: output\raw\financials_batch5_2024_response.txt
